prestashop/__init__.py
prestashop/core.py
prestashop/exceptions.py
prestashop/utils.py
prestashop/version.py
prestashop-0.1.8.dist-info/LICENSE
prestashop-0.1.8.dist-info/METADATA
prestashop-0.1.8.dist-info/WHEEL
prestashop-0.1.8.dist-info/top_level.txt
prestashop-0.1.8.dist-info/RECORD
