Metadata-Version: 2.1
Name: prestashop
Version: 0.1.8
Summary: Prestashop is a library for Python to interact with the PrestaShop's Web Service API.
Home-page: https://github.com/AISYSNEXT-Ltd/prestashop
Author: Aymen Jemi <jemiaymen@gmail.com> (AISYSNEXT)
Author-email: jemiaymen@gmail.com
License: GNU GPL-3
Keywords: prestashop,e-com,e-commerce,prestashop api,api,webservice
Classifier: Programming Language :: Python
Classifier: Programming Language :: Python :: 3.11
Classifier: Programming Language :: Python :: 3.10
Classifier: Programming Language :: Python :: 3.9
Classifier: Programming Language :: Python :: 3.8
Classifier: Development Status :: 4 - Beta
Classifier: Intended Audience :: Developers
Classifier: Topic :: Software Development :: Libraries :: Python Modules
Classifier: Topic :: Internet :: WWW/HTTP :: Site Management
Classifier: Topic :: Internet
License-File: LICENSE
Requires-Dist: requests
Requires-Dist: future
Requires-Dist: packaging
